canns_ripser/_core.cpython-312-x86_64-linux-gnu.so
canns_ripser/__init__.py
canns_ripser/_version.py
canns_ripser-0.4.4.dist-info/METADATA
canns_ripser-0.4.4.dist-info/WHEEL
canns_ripser-0.4.4.dist-info/RECORD
canns_ripser-0.4.4.dist-info/licenses/LICENSE
