Metadata-Version: 2.4
Name: canns-ripser
Version: 0.4.4
Classifier: Development Status :: 4 - Beta
Classifier: Intended Audience :: Developers
Classifier: Intended Audience :: Science/Research
Classifier: Operating System :: OS Independent
Classifier: Programming Language :: Python
Classifier: Programming Language :: Python :: 3
Classifier: Programming Language :: Python :: 3.11
Classifier: Programming Language :: Python :: 3.12
Classifier: Programming Language :: Python :: 3.13
Classifier: Programming Language :: Rust
Classifier: Topic :: Scientific/Engineering :: Mathematics
Classifier: Topic :: Scientific/Engineering :: Information Analysis
Classifier: Typing :: Typed
Requires-Dist: numpy>=1.21.0
Requires-Dist: scipy>=1.7.0
Requires-Dist: scikit-learn>=1.0.0
Requires-Dist: psutil>=7.0.0
Requires-Dist: pytest>=6.0 ; extra == 'dev'
Requires-Dist: pytest-benchmark>=3.4.0 ; extra == 'dev'
Requires-Dist: matplotlib>=3.3.0 ; extra == 'dev'
Requires-Dist: persim>=0.3.0 ; extra == 'dev'
Requires-Dist: ripser>=0.6.12 ; extra == 'dev'
Provides-Extra: dev
License-File: LICENSE
Summary: Rust implementation of Ripser for topological data analysis, optimized for CANNS library
Home-Page: https://github.com/routhleck/canns-ripser
Author-email: Sichao He <sichaohe@outlook.com>
License-Expression: Apache-2.0
Requires-Python: >=3.11, <4.0
Project-URL: Repository, https://github.com/routhleck/canns-ripser
